mvkm_ed/__init__.py
mvkm_ed/core.py
mvkm_ed/datasets.py
mvkm_ed/federated.py
mvkm_ed/mvkm_ed.py
mvkm_ed/utils.py
mvkm_ed-1.0.0.dist-info/licenses/LICENSE
tests/__init__.py
tests/test_core.py
tests/test_federated.py
tests/test_utils.py
mvkm_ed-1.0.0.dist-info/METADATA
mvkm_ed-1.0.0.dist-info/WHEEL
mvkm_ed-1.0.0.dist-info/top_level.txt
mvkm_ed-1.0.0.dist-info/RECORD
